mbinobs/__init__.py
mbinobs/__main__.py
mbinobs/ipv4.py
mbinobs/ipv6.py
mbinobs/mac.py
mbinobs/uuid.py
mbinobs/wrapper.py
mbinobs-1.2.dist-info/METADATA
mbinobs-1.2.dist-info/WHEEL
mbinobs-1.2.dist-info/entry_points.txt
mbinobs-1.2.dist-info/top_level.txt
mbinobs-1.2.dist-info/RECORD
