Metadata-Version: 2.1
Name: mbinobs
Version: 1.2
Summary: Mix bin obfuscator
Home-page: https://github.com/ManuelMaM/mbin-obs
Author: Manuel
Author-email: manumathias2012@gmail.com
License: UNKNOWN
Keywords: obfuscation,obfuscator,ipfuscation
Platform: UNKNOWN
Classifier: Programming Language :: Python :: 3
Classifier: Operating System :: OS Independent
Classifier: License :: OSI Approved :: MIT License
